{
  "manifest": {
    "model": "lightgbm_s2_ukpv_seed44",
    "git_sha": "145fd8e9ddcd8b2b5f0499c1dd5c69ac5ea8f8ff",
    "config_hash": "41d1948fd604dff5",
    "seed": 44,
    "dataset_version": "all_curated.parquet:84057658:1781171196",
    "timestamp_utc": "2026-06-15T13:08:47.003013+00:00",
    "config": {
      "model": [
        "lightgbm"
      ],
      "data": "/Volumes/SSD/standardized-dataset/numerical/all_curated.parquet",
      "split": "test",
      "history": 24,
      "horizon": 12,
      "eval_stride": 12,
      "train_stride": 1,
      "batch_size": 256,
      "seeds": [
        42,
        43,
        44
      ],
      "out": "results",
      "tag": "s2_ukpv",
      "in_domain": false,
      "lopo_dataset": null,
      "train_datasets": [
        "uk_pv"
      ],
      "eval_datasets": [
        "uk_pv"
      ],
      "train_fraction": 1.0,
      "control": "none",
      "model_kwargs": "{}",
      "quantile_levels": [
        0.1,
        0.2,
        0.3,
        0.4,
        0.5,
        0.6,
        0.7,
        0.8,
        0.9
      ],
      "seed": 44
    }
  },
  "results": {
    "overall": {
      "coverage_80": 0.7569394792829242,
      "crps": 0.05608019278540078,
      "nmae": 0.07072685501581809,
      "nmae_per_horizon": [
        0.062499029669607006,
        0.07250082244162878,
        0.07280322872052639,
        0.0720311201870604,
        0.07430463392889138,
        0.0,
        0.0,
        0.0,
        0.0,
        0.0,
        0.0,
        0.0
      ],
      "nmae_ramp": 0.14561558605923144,
      "nrmse": 0.10363018656571643,
      "nrmse_ramp": 0.17618316667526498,
      "quantile_ece": 0.0928634128197904,
      "n_plants": 14.0,
      "n_steps": 49232.0,
      "skill_score": 0.08676654066520673
    },
    "per_plant": {
      "10793": {
        "nmae": 0.09571337565961256,
        "nrmse": 0.1428134598718871,
        "n_steps": 3437.0,
        "nmae_per_horizon": [
          0.07020555340180484,
          0.09122145935987941,
          0.0981481268964065,
          0.1084773680752059,
          0.11444096854147501,
          0.0,
          0.0,
          0.0,
          0.0,
          0.0,
          0.0,
          0.0
        ],
        "nmae_ramp": 0.19607697371231003,
        "nrmse_ramp": 0.2366122873923322,
        "crps": 0.07568172981546308,
        "coverage_80": 0.6779167652130127,
        "quantile_ece": 0.08799987068826172,
        "skill_score": 0.0036993274557091116
      },
      "11176": {
        "nmae": 0.07426913012201589,
        "nrmse": 0.10706275494542257,
        "n_steps": 3453.0,
        "nmae_per_horizon": [
          0.06964684305105538,
          0.07568143789217516,
          0.07379984589382439,
          0.07487659554595333,
          0.0779956106305937,
          0.0,
          0.0,
          0.0,
          0.0,
          0.0,
          0.0,
          0.0
        ],
        "nmae_ramp": 0.1464586938717875,
        "nrmse_ramp": 0.18063116271472468,
        "crps": 0.05755373316225096,
        "coverage_80": 0.7248769402503967,
        "quantile_ece": 0.06753225858351836,
        "skill_score": 0.06958577224401696
      },
      "13388": {
        "nmae": 0.09409572239914527,
        "nrmse": 0.14363286180587434,
        "n_steps": 3431.0,
        "nmae_per_horizon": [
          0.0774361763773533,
          0.09438322522678624,
          0.09549983530595191,
          0.09747970119001644,
          0.10633973576168104,
          0.0,
          0.0,
          0.0,
          0.0,
          0.0,
          0.0,
          0.0
        ],
        "nmae_ramp": 0.19528590438147897,
        "nrmse_ramp": 0.24042924616177694,
        "crps": 0.07536130803799895,
        "coverage_80": 0.7132031321525574,
        "quantile_ece": 0.09130153178535576,
        "skill_score": -0.011540625682056493
      },
      "13817": {
        "nmae": 0.09673773028646662,
        "nrmse": 0.1416622362119315,
        "n_steps": 3536.0,
        "nmae_per_horizon": [
          0.08497908435892913,
          0.10056083150681129,
          0.10531509705972655,
          0.09812126008440984,
          0.09449294533024831,
          0.0,
          0.0,
          0.0,
          0.0,
          0.0,
          0.0,
          0.0
        ],
        "nmae_ramp": 0.1937092619957117,
        "nrmse_ramp": 0.2330415674343288,
        "crps": 0.07693217648374964,
        "coverage_80": 0.665723979473114,
        "quantile_ece": 0.07181372549019607,
        "skill_score": 0.01505437837268897
      },
      "18989": {
        "nmae": 0.08963317196228375,
        "nrmse": 0.1375266261795793,
        "n_steps": 3535.0,
        "nmae_per_horizon": [
          0.07931172469490601,
          0.09241643102364176,
          0.09797436096132045,
          0.08973899297928367,
          0.0886289484460947,
          0.0,
          0.0,
          0.0,
          0.0,
          0.0,
          0.0,
          0.0
        ],
        "nmae_ramp": 0.19854445378170757,
        "nrmse_ramp": 0.24321666281905605,
        "crps": 0.07030425677501492,
        "coverage_80": 0.7315417528152466,
        "quantile_ece": 0.037733773377337736,
        "skill_score": 0.04672533341607865
      },
      "26854": {
        "nmae": 0.04826893622770837,
        "nrmse": 0.07086028037950177,
        "n_steps": 3548.0,
        "nmae_per_horizon": [
          0.04338941155643813,
          0.046949134655864366,
          0.046503171038987386,
          0.04783577367920049,
          0.057553988866180114,
          0.0,
          0.0,
          0.0,
          0.0,
          0.0,
          0.0,
          0.0
        ],
        "nmae_ramp": 0.10804796910379082,
        "nrmse_ramp": 0.12876857405403488,
        "crps": 0.03829048287896397,
        "coverage_80": 0.8627395629882812,
        "quantile_ece": 0.027877990730301887,
        "skill_score": 0.020453623285636602
      },
      "26933": {
        "nmae": 0.04435234658000235,
        "nrmse": 0.06392883719073347,
        "n_steps": 3551.0,
        "nmae_per_horizon": [
          0.04853600336986276,
          0.05009726110882992,
          0.04302278579177235,
          0.03885540624277615,
          0.04098214231459725,
          0.0,
          0.0,
          0.0,
          0.0,
          0.0,
          0.0,
          0.0
        ],
        "nmae_ramp": 0.0862932003247486,
        "nrmse_ramp": 0.10942279327348227,
        "crps": 0.0354399134306039,
        "coverage_80": 0.8732751607894897,
        "quantile_ece": 0.03287023999499358,
        "skill_score": 0.37685250626230204
      },
      "27020": {
        "nmae": 0.03819045292177099,
        "nrmse": 0.05192531174972687,
        "n_steps": 3455.0,
        "nmae_per_horizon": [
          0.04024642103934807,
          0.044075552238155895,
          0.04164642420891616,
          0.03388047873754058,
          0.030170041293393984,
          0.0,
          0.0,
          0.0,
          0.0,
          0.0,
          0.0,
          0.0
        ],
        "nmae_ramp": 0.07625040310987197,
        "nrmse_ramp": 0.08949277495229407,
        "crps": 0.03207978209543337,
        "coverage_80": 0.7777134776115417,
        "quantile_ece": 0.15415661681942433,
        "skill_score": 0.28946137609324984
      },
      "3432": {
        "nmae": 0.04986066396308682,
        "nrmse": 0.06939037918436257,
        "n_steps": 3576.0,
        "nmae_per_horizon": [
          0.04946099328368876,
          0.05194753124806788,
          0.051064103566839936,
          0.04870737955422594,
          0.048141339083050724,
          0.0,
          0.0,
          0.0,
          0.0,
          0.0,
          0.0,
          0.0
        ],
        "nmae_ramp": 0.09977115319685313,
        "nrmse_ramp": 0.12146568211646283,
        "crps": 0.04057502437540886,
        "coverage_80": 0.8154362440109253,
        "quantile_ece": 0.15715883668903805,
        "skill_score": 0.28597200395861155
      },
      "6648": {
        "nmae": 0.05503878482833476,
        "nrmse": 0.07775722874989814,
        "n_steps": 3535.0,
        "nmae_per_horizon": [
          0.055177670457914905,
          0.06047600410416243,
          0.05746833383282188,
          0.05259545775282269,
          0.04898711188141484,
          0.0,
          0.0,
          0.0,
          0.0,
          0.0,
          0.0,
          0.0
        ],
        "nmae_ramp": 0.10029763174878265,
        "nrmse_ramp": 0.12581686784061574,
        "crps": 0.043465215062419314,
        "coverage_80": 0.8070721626281738,
        "quantile_ece": 0.05307245010215308,
        "skill_score": 0.18780596658204285
      },
      "7315": {
        "nmae": 0.06965130011114853,
        "nrmse": 0.10061004315749263,
        "n_steps": 3524.0,
        "nmae_per_horizon": [
          0.061895388659963586,
          0.06932792312030864,
          0.0688494453602799,
          0.07205621602415181,
          0.07689328861587064,
          0.0,
          0.0,
          0.0,
          0.0,
          0.0,
          0.0,
          0.0
        ],
        "nmae_ramp": 0.1464735086311438,
        "nrmse_ramp": 0.17078736515581466,
        "crps": 0.053600752592789826,
        "coverage_80": 0.7667423486709595,
        "quantile_ece": 0.17344557951822426,
        "skill_score": 0.05586506656434409
      },
      "7756": {
        "nmae": 0.07786489497227106,
        "nrmse": 0.11763574446023058,
        "n_steps": 3531.0,
        "nmae_per_horizon": [
          0.07239541975551503,
          0.0852279451457636,
          0.07973913437889298,
          0.07570635017216797,
          0.07614245325270196,
          0.0,
          0.0,
          0.0,
          0.0,
          0.0,
          0.0,
          0.0
        ],
        "nmae_ramp": 0.1737676936406958,
        "nrmse_ramp": 0.21062132131574351,
        "crps": 0.06149930562166587,
        "coverage_80": 0.7264230847358704,
        "quantile_ece": 0.04536014349098463,
        "skill_score": 0.027737454829211527
      },
      "8066": {
        "nmae": 0.1042962228467379,
        "nrmse": 0.15523185189493305,
        "n_steps": 3515.0,
        "nmae_per_horizon": [
          0.0844372199020335,
          0.10222752174353347,
          0.10507365949919643,
          0.1105164013354168,
          0.12146224025399771,
          0.0,
          0.0,
          0.0,
          0.0,
          0.0,
          0.0,
          0.0
        ],
        "nmae_ramp": 0.21469677222807734,
        "nrmse_ramp": 0.2610107149156179,
        "crps": 0.08369240703035433,
        "coverage_80": 0.6492176651954651,
        "quantile_ece": 0.08131816026552868,
        "skill_score": 0.007725069440584154
      },
      "9191": {
        "nmae": 0.052203237340868375,
        "nrmse": 0.07078499613845661,
        "n_steps": 3605.0,
        "nmae_per_horizon": [
          0.037868505465684724,
          0.050419255808822845,
          0.05514087829243242,
          0.05958830124567377,
          0.05803406073317928,
          0.0,
          0.0,
          0.0,
          0.0,
          0.0,
          0.0,
          0.0
        ],
        "nmae_ramp": 0.10294458510228045,
        "nrmse_ramp": 0.11524731330742552,
        "crps": 0.04064661163349396,
        "coverage_80": 0.8052704334259033,
        "quantile_ece": 0.21844660194174756,
        "skill_score": 0.059205845671972956
      }
    }
  }
}
